<?xml version="1.0" encoding="utf-8"?>
<AssetDeclaration xmlns="uri:ea.com:eala:asset" xmlns:xsi="http://www.w3.org/2001/XMLSchema-instance">
	<Tags></Tags>
	<Includes>
		<Include
			type="all"
			source="ART:ARRamp440B.w3x" />
		<Include
			type="instance"
			source="DATA:BaseObjects/BaseRamp.xml" />
	</Includes>
	<GameObject
		id="ARRamp440B"
		inheritFrom="BaseRamp"
		EditorName="ARRamp440B"
		Browser="REGION ARCTIC_AR MISC_MAN_MADE">
		<Draws>
			<ScriptedModelDraw
				id="ModuleTag_Draw"
				OkToChangeModelColor="true">
				<ModelConditionState
					ParseCondStateType="PARSE_DEFAULT">
					<Model
						Name="ARRamp440B" />
				</ModelConditionState>
			</ScriptedModelDraw>
		</Draws>
		<!-- The following Geometry info is generated from RtsAssetTool on 10/29/2009 3:57 PM -->
		<Geometry>
			<Shape
				Type = "BOX"
				MajorRadius = "233.2074"
				MinorRadius = "138.6238"
				Height = "61.78362"
				ContactPointGeneration = "NONE" >
				<Offset
					x = "7.629395E-06"
					y = "110.844"
					z = "-1.671019" />
			</Shape>
		</Geometry>
	</GameObject>
</AssetDeclaration>
