<?xml version="1.0" encoding="utf-8"?>
<AssetDeclaration xmlns="uri:ea.com:eala:asset" xmlns:xsi="http://www.w3.org/2001/XMLSchema-instance">
  <Tags></Tags>
  <Includes>
    <Include
			type="all"
			source="ART:ARSeawall02.w3x" />
    <Include
			type="instance"
			source="DATA:BaseObjects/BaseProp.xml" />
  </Includes>
  <GameObject
		id="ARSeawall02"
		inheritFrom="BaseProp"
		EditorName="ARSeawall02"
		Browser="REGION ARCTIC_AR MISC_MAN_MADE">
    <Draws>
      <ScriptedModelDraw
				id="ModuleTag_Draw">
        <ModelConditionState
					ParseCondStateType="PARSE_DEFAULT">
          <Model
						Name="ARSeawall02" />
        </ModelConditionState>
      </ScriptedModelDraw>
    </Draws>
    <!-- The following Geometry info is generated from RtsAssetTool on 10/29/2009 3:57 PM -->
    <Geometry>
    	<Shape
    		Type = "BOX"
    		MajorRadius = "100.986"
    		MinorRadius = "14.03173"
    		Height = "108.9731"
    		ContactPointGeneration = "NONE" >
    		<Offset
    			x = "-0.004039764"
    			y = "28.32652"
    			z = "-42.12588" />
    	</Shape>
    </Geometry>
  </GameObject>
</AssetDeclaration>
