<?xml version="1.0" encoding="us-ascii"?>
<AssetDeclaration xmlns="uri:ea.com:eala:asset" xmlns:xsi="http://www.w3.org/2001/XMLSchema-instance" xmlns:xai="uri:ea.com:eala:asset:instance">
	<Tags></Tags>
		<Includes>
			<Include
				type="instance"
				source="NodAircraftFInfantry.xml"/>
	</Includes>
	<GameObject
		id="NodAircraftF_Infantry_Base"
		inheritFrom="NodAircraftFInfantry"
		KindOf="PRELOAD CAN_CAST_REFLECTIONS CAN_ATTACK SELECTABLE AIRCRAFT VEHICLE TRANSPORT SUMMONED IGNORES_SELECT_ALL">
		<Behaviors>
			<HordeTransportContain
				xai:joinAction="Overwrite"
				id="ModuleTag_Contain"
				ObjectStatusOfContained="UNSELECTABLE"
				ContainMax="3"
				AllowEnemiesInside="false"
				AllowAlliesInside="false"
				AllowNeutralInside="false"
				AllowOwnPlayerInsideOverride="true"
				ShowPips="true"
				EnterSound="VehicleEnter"
				ExitSound="VehicleExit"
				KillPassengersOnDeath="true">
				<PassengerFilter
					Rule="ANY"
					Include="INFANTRY" />
				<DieMuxData
					DeathTypes="ALL" />
			</HordeTransportContain>
			
		</Behaviors>
	</GameObject>
</AssetDeclaration>
