<?xml version="1.0" encoding="utf-8"?>
<AssetDeclaration xmlns="uri:ea.com:eala:asset" xmlns:xsi="http://www.w3.org/2001/XMLSchema-instance">
	<Tags></Tags>
	<Includes>
		<Include
			type="all"
			source="ART:JTA_trashcube01.w3x" />
		<Include
			type="instance"
			source="DATA:BaseObjects/BaseTerrainPlate.xml" />
	</Includes>
	<GameObject
		id="JTA_trashcube01"
		inheritFrom="BaseTerrainPlate"
		Side="Civilian"
		EditorName="JTA_trashcube01"
		Browser="REGION JUNKTOWN_JT MISC_MAN_MADE">
	  <DisplayName
			xai:joinAction="Replace" xmlns:xai="uri:ea.com:eala:asset:instance">Prop</DisplayName>
		<Draws>
			<ScriptedModelDraw
				id="ModuleTag_Draw">
				<ModelConditionState
					ParseCondStateType="PARSE_DEFAULT">
					<Model
						Name="JTA_trashcube01" />
				</ModelConditionState>
			</ScriptedModelDraw>
		</Draws>
		<!-- The following Geometry info is generated from RtsAssetTool on 10/30/2009 10:33 AM -->
		<Geometry>
			<Shape
				Type = "BOX"
				MajorRadius = "210.5305"
				MinorRadius = "209.0654"
				Height = "120.6596"
				ContactPointGeneration = "NONE" >
				<Offset
					x = "-0.5011444"
					y = "-0.9802704"
					z = "-120.0096" />
			</Shape>
		</Geometry>
	</GameObject>
</AssetDeclaration>
