<?xml version="1.0" encoding="UTF-8"?>
<AssetDeclaration xmlns="uri:ea.com:eala:asset" xmlns:xsi="http://www.w3.org/2001/XMLSchema-instance">
	<Includes>
		<Include source="art:fxcloudcr01.xml" type="instance"/>
	</Includes>
	<FXParticleSystemTemplate ParticleTexture="FXCloudCR01" PerParticleAttachedSystem="" Priority="MEDIUM_OR_ABOVE" SortLevel="1" SystemLifetime="3" Type="GPU_PARTICLE" id="IonCannonPreExpl_CloudColumn">
		<Lifetime High="150" Low="100"/>
		<Size High="3" Low="1"/>
		<BurstCount High="10" Low="10"/>
		<InitialDelay High="90" Low="90"/>
		<Colors>
			<Color Frame="2" RelativeAge="9.999999">
				<Color b="1" g="0.886275" r="0.541177"/>
			</Color>
			<Color Frame="3" RelativeAge="66">
				<Color b="1" g="0.588235" r="0.25098"/>
			</Color>
			<Color Frame="4" RelativeAge="100">
				<Color b="0" g="0" r="0"/>
			</Color>
			<ColorScale High="3" Low="2"/>
		</Colors>
		<Physics>
			<Default>
				<VelocityDamping High="0.99" Low="0.9"/>
				<DriftVelocity x="0" y="0" z="0.15"/>
			</Default>
		</Physics>
		<Draw>
			<Gpu SpeedMultiplier="1"/>
		</Draw>
		<Volume>
			<Cylinder Length="100" Radius="50">
				<Offset x="0" y="0" z="50"/>
			</Cylinder>
		</Volume>
		<Velocity>
			<Ortho>
				<Position>
					<x High="0" Low="0"/>
					<y High="0" Low="0"/>
					<z High="3" Low="1"/>
				</Position>
			</Ortho>
		</Velocity>
		<Event/>
		<Update>
			<Default Rotation="ROTATE_AROUND_VELOCITY">
				<SizeRate High="2" Low="0.5"/>
				<SizeRateDamping High="0.9" Low="0.8"/>
				<AngleZ High="7" Low="-7"/>
				<AngularRateZ High="0.2" Low="-0.2"/>
				<AngularDamping High="1" Low="0.75"/>
				<AngleXY High="0.5" Low="-0.5"/>
				<AngularRateXY High="1" Low="1"/>
				<AngularDampingXY High="1" Low="1"/>
			</Default>
		</Update>
	</FXParticleSystemTemplate>
</AssetDeclaration>